torch_segment_fiducials_2d/__init__.py
torch_segment_fiducials_2d/_cli.py
torch_segment_fiducials_2d/constants.py
torch_segment_fiducials_2d/predict.py
torch_segment_fiducials_2d/train.py
torch_segment_fiducials_2d/utils.py
torch_segment_fiducials_2d/dataset/__init__.py
torch_segment_fiducials_2d/dataset/augmentation.py
torch_segment_fiducials_2d/dataset/download.py
torch_segment_fiducials_2d/dataset/training_datamodule.py
torch_segment_fiducials_2d/dataset/training_dataset.py
torch_segment_fiducials_2d/model/__init__.py
torch_segment_fiducials_2d/model/_pretrained_weights.py
torch_segment_fiducials_2d/model/dice.py
torch_segment_fiducials_2d/model/model.py
torch_segment_fiducials_2d/model/model_parts.py
torch_segment_fiducials_2d-0.1.2.dist-info/METADATA
torch_segment_fiducials_2d-0.1.2.dist-info/WHEEL
torch_segment_fiducials_2d-0.1.2.dist-info/entry_points.txt
torch_segment_fiducials_2d-0.1.2.dist-info/licenses/LICENSE
torch_segment_fiducials_2d-0.1.2.dist-info/RECORD
