Metadata-Version: 2.4
Name: torch-segment-fiducials-2d
Version: 0.1.2
Summary: A small pre-trained residual U-Net for gold fiducial segmentation in cryo-EM images
Project-URL: homepage, https://github.com/teamtomo/torch-segment-fiducials-2d
Project-URL: repository, https://github.com/teamtomo/torch-segment-fiducials-2d
Author-email: Alister Burt <alisterburt@gmail.com>
License: BSD-3-Clause
License-File: LICENSE
Classifier: Development Status :: 3 - Alpha
Classifier: License :: OSI Approved :: BSD License
Classifier: Programming Language :: Python :: 3
Classifier: Programming Language :: Python :: 3.10
Classifier: Programming Language :: Python :: 3.11
Classifier: Programming Language :: Python :: 3.12
Classifier: Programming Language :: Python :: 3.13
Classifier: Typing :: Typed
Requires-Python: >=3.10
Requires-Dist: einops
Requires-Dist: imageio
Requires-Dist: lightning
Requires-Dist: mrcfile
Requires-Dist: notebook>=7.4.3
Requires-Dist: numpy
Requires-Dist: pooch
Requires-Dist: scipy
Requires-Dist: tiler
Requires-Dist: torch
Requires-Dist: torch-fourier-rescale>=0.1.1
Requires-Dist: torchvision
Requires-Dist: typer
Requires-Dist: zenodo-get
Provides-Extra: dev
Requires-Dist: ipython; extra == 'dev'
Requires-Dist: pdbpp; extra == 'dev'
Requires-Dist: rich; extra == 'dev'
Provides-Extra: test
Requires-Dist: pytest; extra == 'test'
Requires-Dist: pytest-cov; extra == 'test'
